{"name":"A5","tags":[],"isDraft":false,"layout":{"format":"A5","unit":"cm","orientation":"portrait","rotation":0,"margins":{"top":0.5,"left":0.5,"right":0.5,"bottom":0.5},"emptyLabels":0,"width":14.8,"height":21,"repeatLayout":null},"pages":[{"width":14.8,"height":21,"conditionalFormats":[],"backgroundImage":null,"layout":[],"components":[{"id":"","top":0,"left":0,"width":13.76,"height":3.39,"zindex":1003,"className":null,"cls":"labelComponent","value":"KARTA WIN","dataIndex":"","borderStatus":{"top":true,"right":true,"bottom":true,"left":true},"borderWidth":0,"borderColor":"#000000","borderStyle":"none","backgroundColor":"","useFlexHeight":true,"isEditable":false,"autoShrink":false,"isPlainHTML":false,"padding":{"top":0,"right":0.2,"bottom":0,"left":0},"conditionalFormats":[],"enableArrayFunctions":true,"lockPosition":false,"fontFamily":"opensans","fontAlign":"center","fontSize":34,"fontType":[],"fontColor":"#000000","lineHeight":1.15,"textDirection":"ltr","textColumns":1,"dynamicFontSize":false,"formatter":{"type":"text","values":null},"fontValign":"middle"},{"id":"","top":4.1,"left":0,"width":13.76,"height":4.66,"zindex":1001,"className":null,"cls":"compositeComponent","value":null,"dataIndex":"wines","borderStatus":{"top":true,"right":true,"bottom":true,"left":true},"borderWidth":0,"borderColor":"#000000","borderStyle":"none","backgroundColor":"","useFlexHeight":true,"isEditable":false,"autoShrink":false,"isPlainHTML":false,"padding":{"top":0,"right":0.2,"bottom":0,"left":0},"conditionalFormats":[],"enableArrayFunctions":true,"lockPosition":false,"whitespace":5,"allowRowSplit":true,"components":[{"id":"","top":0,"left":0,"width":2.6,"height":4.47,"zindex":1002,"className":null,"cls":"imageComponent","value":"{wines::image}","dataIndex":null,"borderStatus":{"top":true,"right":true,"bottom":true,"left":true},"borderWidth":0,"borderColor":"#000000","borderStyle":"none","backgroundColor":"","useFlexHeight":true,"isEditable":false,"autoShrink":false,"isPlainHTML":false,"padding":{"top":0,"right":0.2,"bottom":0,"left":0},"conditionalFormats":[],"enableArrayFunctions":true,"lockPosition":false,"fontFamily":"opensans","fontAlign":"left","fontSize":12,"fontType":[],"fontColor":"#000000","lineHeight":1.15,"textDirection":"ltr","textColumns":1,"dynamicFontSize":false,"autoScale":true,"autoRotate":false,"align":"left","fontValign":"top"},{"id":"","top":0,"left":2.7,"width":8,"height":1.2,"zindex":1002,"className":null,"cls":"labelComponent","value":"{name}","dataIndex":"","borderStatus":{"top":true,"right":true,"bottom":true,"left":true},"borderWidth":0,"borderColor":"#000000","borderStyle":"none","backgroundColor":"","useFlexHeight":true,"isEditable":false,"autoShrink":false,"isPlainHTML":false,"padding":{"top":0,"right":0.2,"bottom":0,"left":0},"conditionalFormats":[],"enableArrayFunctions":true,"lockPosition":false,"fontFamily":"opensans","fontAlign":"left","fontSize":18,"fontType":["bold"],"fontColor":"#000000","lineHeight":1.15,"textDirection":"ltr","textColumns":1,"dynamicFontSize":false,"formatter":{"type":"text","values":null},"fontValign":"top"},{"id":"","top":1.22,"left":2.7,"width":7.75,"height":0.4,"zindex":1002,"className":null,"cls":"labelComponent","value":"Szczep: {szczepy}","dataIndex":"","borderStatus":{"top":true,"right":true,"bottom":true,"left":true},"borderWidth":0,"borderColor":"#000000","borderStyle":"none","backgroundColor":"","useFlexHeight":true,"isEditable":false,"autoShrink":false,"isPlainHTML":false,"padding":{"top":0,"right":0.2,"bottom":0,"left":0},"conditionalFormats":[],"enableArrayFunctions":true,"lockPosition":false,"fontFamily":"opensans","fontAlign":"left","fontSize":12,"fontType":["bold"],"fontColor":"#000000","lineHeight":1.15,"textDirection":"ltr","textColumns":1,"dynamicFontSize":false,"formatter":{"type":"text","values":null},"fontValign":"top"},{"id":"","top":1.6,"left":2.7,"width":8.02,"height":0.4,"zindex":1002,"className":null,"cls":"labelComponent","value":"Region: {region}","dataIndex":"","borderStatus":{"top":true,"right":true,"bottom":true,"left":true},"borderWidth":0,"borderColor":"#000000","borderStyle":"none","backgroundColor":"","useFlexHeight":true,"isEditable":false,"autoShrink":false,"isPlainHTML":false,"padding":{"top":0,"right":0.2,"bottom":0,"left":0},"conditionalFormats":[],"enableArrayFunctions":true,"lockPosition":false,"fontFamily":"opensans","fontAlign":"left","fontSize":12,"fontType":["bold"],"fontColor":"#000000","lineHeight":1.15,"textDirection":"ltr","textColumns":1,"dynamicFontSize":false,"formatter":{"type":"text","values":null},"fontValign":"top"},{"id":"","top":1.95,"left":2.7,"width":8.62,"height":0.4,"zindex":1002,"className":null,"cls":"labelComponent","value":"Typ: {type}","dataIndex":"","borderStatus":{"top":true,"right":true,"bottom":true,"left":true},"borderWidth":0,"borderColor":"#000000","borderStyle":"none","backgroundColor":"","useFlexHeight":true,"isEditable":false,"autoShrink":false,"isPlainHTML":false,"padding":{"top":0,"right":0.2,"bottom":0,"left":0},"conditionalFormats":[],"enableArrayFunctions":true,"lockPosition":false,"fontFamily":"opensans","fontAlign":"left","fontSize":12,"fontType":["bold"],"fontColor":"#000000","lineHeight":1.15,"textDirection":"ltr","textColumns":1,"dynamicFontSize":false,"formatter":{"type":"text","values":null},"fontValign":"top"},{"id":"","top":2.49,"left":2.7,"width":11.03,"height":1.46,"zindex":1002,"className":null,"cls":"labelComponent","value":"{description}","dataIndex":"","borderStatus":{"top":true,"right":true,"bottom":true,"left":true},"borderWidth":0,"borderColor":"#000000","borderStyle":"none","backgroundColor":"","useFlexHeight":true,"isEditable":false,"autoShrink":false,"isPlainHTML":false,"padding":{"top":0,"right":0.2,"bottom":0,"left":0},"conditionalFormats":[],"enableArrayFunctions":true,"lockPosition":false,"fontFamily":"opensans","fontAlign":"left","fontSize":12,"fontType":[],"fontColor":"#000000","lineHeight":1.15,"textDirection":"ltr","textColumns":1,"dynamicFontSize":false,"formatter":{"type":"text","values":null},"fontValign":"top"},{"id":"","top":4.02,"left":2.7,"width":8.62,"height":0.5,"zindex":1002,"className":null,"cls":"labelComponent","value":"Vol: {alcohol}","dataIndex":"","borderStatus":{"top":true,"right":true,"bottom":true,"left":true},"borderWidth":0,"borderColor":"#000000","borderStyle":"none","backgroundColor":"","useFlexHeight":true,"isEditable":false,"autoShrink":false,"isPlainHTML":false,"padding":{"top":0,"right":0.2,"bottom":0,"left":0},"conditionalFormats":[],"enableArrayFunctions":true,"lockPosition":false,"fontFamily":"opensans","fontAlign":"left","fontSize":12,"fontType":[],"fontColor":"#696969","lineHeight":1.15,"textDirection":"ltr","textColumns":1,"dynamicFontSize":false,"formatter":{"type":"text","values":null},"fontValign":"top"},{"id":"","top":0.66,"left":12.22,"width":1.51,"height":0.61,"zindex":1002,"className":null,"cls":"labelComponent","value":"120zł","dataIndex":"","borderStatus":{"top":true,"right":true,"bottom":true,"left":true},"borderWidth":0,"borderColor":"#000000","borderStyle":"none","backgroundColor":"","useFlexHeight":true,"isEditable":false,"autoShrink":false,"isPlainHTML":false,"padding":{"top":0,"right":0.2,"bottom":0,"left":0},"conditionalFormats":[],"enableArrayFunctions":true,"lockPosition":false,"fontFamily":"opensans","fontAlign":"left","fontSize":18,"fontType":["bold"],"fontColor":"#000000","lineHeight":1.15,"textDirection":"ltr","textColumns":1,"dynamicFontSize":false,"formatter":{"type":"text","values":null},"fontValign":"top"},{"id":"","top":0.13,"left":10.95,"width":1.22,"height":0.4,"zindex":1002,"className":null,"cls":"labelComponent","value":"150ml","dataIndex":"","borderStatus":{"top":true,"right":true,"bottom":true,"left":true},"borderWidth":0,"borderColor":"#000000","borderStyle":"none","backgroundColor":"","useFlexHeight":true,"isEditable":false,"autoShrink":false,"isPlainHTML":false,"padding":{"top":0,"right":0.2,"bottom":0,"left":0},"conditionalFormats":[],"enableArrayFunctions":true,"lockPosition":false,"fontFamily":"opensans","fontAlign":"left","fontSize":12,"fontType":[],"fontColor":"#000000","lineHeight":1.15,"textDirection":"ltr","textColumns":1,"dynamicFontSize":false,"formatter":{"type":"text","values":null},"fontValign":"top"},{"id":"","top":0.82,"left":10.95,"width":1.22,"height":0.4,"zindex":1002,"className":null,"cls":"labelComponent","value":"750ml","dataIndex":"","borderStatus":{"top":true,"right":true,"bottom":true,"left":true},"borderWidth":0,"borderColor":"#000000","borderStyle":"none","backgroundColor":"","useFlexHeight":true,"isEditable":false,"autoShrink":false,"isPlainHTML":false,"padding":{"top":0,"right":0.2,"bottom":0,"left":0},"conditionalFormats":[],"enableArrayFunctions":true,"lockPosition":false,"fontFamily":"opensans","fontAlign":"left","fontSize":12,"fontType":[],"fontColor":"#000000","lineHeight":1.15,"textDirection":"ltr","textColumns":1,"dynamicFontSize":false,"formatter":{"type":"text","values":null},"fontValign":"top"},{"id":"","top":0,"left":12.22,"width":1.51,"height":0.61,"zindex":1002,"className":null,"cls":"labelComponent","value":"120zł","dataIndex":"","borderStatus":{"top":true,"right":true,"bottom":true,"left":true},"borderWidth":0,"borderColor":"#000000","borderStyle":"none","backgroundColor":"","useFlexHeight":true,"isEditable":false,"autoShrink":false,"isPlainHTML":false,"padding":{"top":0,"right":0.2,"bottom":0,"left":0},"conditionalFormats":[],"enableArrayFunctions":true,"lockPosition":false,"fontFamily":"opensans","fontAlign":"left","fontSize":18,"fontType":["bold"],"fontColor":"#000000","lineHeight":1.15,"textDirection":"ltr","textColumns":1,"dynamicFontSize":false,"formatter":{"type":"text","values":null},"fontValign":"top"}],"sortBy":[],"sortDir":"ASC","filterBy":[],"groupBy":[],"iterateLeftToRight":false},{"id":"win","top":1.01,"left":0,"width":0,"height":0,"zindex":1004,"className":null,"cls":"tableComponent","value":null,"dataIndex":"wines","borderStatus":{"top":true,"right":true,"bottom":true,"left":true},"borderWidth":1,"borderColor":"#000000","borderStyle":"solid","backgroundColor":"","useFlexHeight":true,"isEditable":false,"autoShrink":false,"isPlainHTML":false,"padding":{"top":0.07,"right":0.07,"bottom":0.07,"left":0.07},"conditionalFormats":[],"enableArrayFunctions":true,"lockPosition":false,"fontFamily":"opensans","fontAlign":"left","fontSize":12,"fontType":[],"fontColor":"#000000","lineHeight":1.15,"textDirection":"ltr","textColumns":1,"dynamicFontSize":false,"rows":[{"isHeader":true,"isStatic":true,"columns":[{"id":"","top":0,"left":0,"width":2.65,"height":0,"zindex":1000,"phpClassName":"Reports_Component_CustomText","className":null,"cls":"labelComponent","name":null,"preview":null,"value":"alcohol","defaultValue":null,"dataIndex":"randomDataIndexForFlexHeight","borderStatus":{"top":true,"right":true,"bottom":false,"left":true},"borderWidth":1,"borderColor":"#000000","borderStyle":"solid","backgroundColor":"#ededed","useFlexHeight":true,"isEditable":false,"autoShrink":false,"isPlainHTML":false,"padding":{"top":0.08,"right":0.08,"bottom":0.08,"left":0.08},"conditionalFormats":[],"enableArrayFunctions":true,"lockPosition":false,"fontFamily":"opensans","fontAlign":"left","fontSize":12,"fontType":["bold"],"fontColor":"#000000","valign":"bottom","lineHeight":1.15,"textDirection":"ltr","textColumns":1,"dynamicFontSize":false,"formatter":{"type":"text","values":null}},{"id":"","top":0,"left":0,"width":2.65,"height":0,"zindex":1000,"phpClassName":"Reports_Component_CustomText","className":null,"cls":"labelComponent","name":null,"preview":null,"value":"catalogNumber","defaultValue":null,"dataIndex":"randomDataIndexForFlexHeight","borderStatus":{"top":true,"right":true,"bottom":false,"left":true},"borderWidth":1,"borderColor":"#000000","borderStyle":"solid","backgroundColor":"#ededed","useFlexHeight":true,"isEditable":false,"autoShrink":false,"isPlainHTML":false,"padding":{"top":0.08,"right":0.08,"bottom":0.08,"left":0.08},"conditionalFormats":[],"enableArrayFunctions":true,"lockPosition":false,"fontFamily":"opensans","fontAlign":"left","fontSize":12,"fontType":["bold"],"fontColor":"#000000","valign":"bottom","lineHeight":1.15,"textDirection":"ltr","textColumns":1,"dynamicFontSize":false,"formatter":{"type":"text","values":null}},{"id":"","top":0,"left":0,"width":2.65,"height":0,"zindex":1000,"phpClassName":"Reports_Component_CustomText","className":null,"cls":"labelComponent","name":null,"preview":null,"value":"category","defaultValue":null,"dataIndex":"randomDataIndexForFlexHeight","borderStatus":{"top":true,"right":true,"bottom":false,"left":true},"borderWidth":1,"borderColor":"#000000","borderStyle":"solid","backgroundColor":"#ededed","useFlexHeight":true,"isEditable":false,"autoShrink":false,"isPlainHTML":false,"padding":{"top":0.08,"right":0.08,"bottom":0.08,"left":0.08},"conditionalFormats":[],"enableArrayFunctions":true,"lockPosition":false,"fontFamily":"opensans","fontAlign":"left","fontSize":12,"fontType":["bold"],"fontColor":"#000000","valign":"bottom","lineHeight":1.15,"textDirection":"ltr","textColumns":1,"dynamicFontSize":false,"formatter":{"type":"text","values":null}},{"id":"","top":0,"left":0,"width":2.65,"height":0,"zindex":1000,"phpClassName":"Reports_Component_CustomText","className":null,"cls":"labelComponent","name":null,"preview":null,"value":"description","defaultValue":null,"dataIndex":"randomDataIndexForFlexHeight","borderStatus":{"top":true,"right":true,"bottom":false,"left":true},"borderWidth":1,"borderColor":"#000000","borderStyle":"solid","backgroundColor":"#ededed","useFlexHeight":true,"isEditable":false,"autoShrink":false,"isPlainHTML":false,"padding":{"top":0.08,"right":0.08,"bottom":0.08,"left":0.08},"conditionalFormats":[],"enableArrayFunctions":true,"lockPosition":false,"fontFamily":"opensans","fontAlign":"left","fontSize":12,"fontType":["bold"],"fontColor":"#000000","valign":"bottom","lineHeight":1.15,"textDirection":"ltr","textColumns":1,"dynamicFontSize":false,"formatter":{"type":"text","values":null}},{"id":"","top":0,"left":0,"width":2.65,"height":0,"zindex":1000,"phpClassName":"Reports_Component_CustomText","className":null,"cls":"labelComponent","name":null,"preview":null,"value":"id","defaultValue":null,"dataIndex":"randomDataIndexForFlexHeight","borderStatus":{"top":true,"right":true,"bottom":false,"left":true},"borderWidth":1,"borderColor":"#000000","borderStyle":"solid","backgroundColor":"#ededed","useFlexHeight":true,"isEditable":false,"autoShrink":false,"isPlainHTML":false,"padding":{"top":0.08,"right":0.08,"bottom":0.08,"left":0.08},"conditionalFormats":[],"enableArrayFunctions":true,"lockPosition":false,"fontFamily":"opensans","fontAlign":"left","fontSize":12,"fontType":["bold"],"fontColor":"#000000","valign":"bottom","lineHeight":1.15,"textDirection":"ltr","textColumns":1,"dynamicFontSize":false,"formatter":{"type":"text","values":null}},{"id":"","top":0,"left":0,"width":2.65,"height":0,"zindex":1000,"phpClassName":"Reports_Component_CustomText","className":null,"cls":"labelComponent","name":null,"preview":null,"value":"image","defaultValue":null,"dataIndex":"randomDataIndexForFlexHeight","borderStatus":{"top":true,"right":true,"bottom":false,"left":true},"borderWidth":1,"borderColor":"#000000","borderStyle":"solid","backgroundColor":"#ededed","useFlexHeight":true,"isEditable":false,"autoShrink":false,"isPlainHTML":false,"padding":{"top":0.08,"right":0.08,"bottom":0.08,"left":0.08},"conditionalFormats":[],"enableArrayFunctions":true,"lockPosition":false,"fontFamily":"opensans","fontAlign":"left","fontSize":12,"fontType":["bold"],"fontColor":"#000000","valign":"bottom","lineHeight":1.15,"textDirection":"ltr","textColumns":1,"dynamicFontSize":false,"formatter":{"type":"text","values":null}},{"id":"","top":0,"left":0,"width":2.65,"height":0,"zindex":1000,"phpClassName":"Reports_Component_CustomText","className":null,"cls":"labelComponent","name":null,"preview":null,"value":"name","defaultValue":null,"dataIndex":"randomDataIndexForFlexHeight","borderStatus":{"top":true,"right":true,"bottom":false,"left":true},"borderWidth":1,"borderColor":"#000000","borderStyle":"solid","backgroundColor":"#ededed","useFlexHeight":true,"isEditable":false,"autoShrink":false,"isPlainHTML":false,"padding":{"top":0.08,"right":0.08,"bottom":0.08,"left":0.08},"conditionalFormats":[],"enableArrayFunctions":true,"lockPosition":false,"fontFamily":"opensans","fontAlign":"left","fontSize":12,"fontType":["bold"],"fontColor":"#000000","valign":"bottom","lineHeight":1.15,"textDirection":"ltr","textColumns":1,"dynamicFontSize":false,"formatter":{"type":"text","values":null}}]},{"isHeader":false,"isStatic":false,"columns":[{"id":"","top":0,"left":0,"width":2.65,"height":0,"zindex":1000,"phpClassName":"Reports_Component_CustomText","className":null,"cls":"labelComponent","name":null,"preview":null,"value":"{alcohol}","defaultValue":null,"dataIndex":"","borderStatus":{"top":true,"right":true,"bottom":true,"left":true},"borderWidth":0,"borderColor":"#000000","borderStyle":"none","backgroundColor":"","useFlexHeight":true,"isEditable":false,"autoShrink":false,"isPlainHTML":false,"padding":{"top":0.08,"right":0.08,"bottom":0.08,"left":0.08},"conditionalFormats":[],"enableArrayFunctions":true,"lockPosition":false,"fontFamily":"opensans","fontAlign":"left","fontSize":12,"fontType":[],"fontColor":"#000000","valign":"top","lineHeight":1.15,"textDirection":"ltr","textColumns":1,"dynamicFontSize":false,"formatter":{"type":"text","values":null}},{"id":"","top":0,"left":0,"width":2.65,"height":0,"zindex":1000,"phpClassName":"Reports_Component_CustomText","className":null,"cls":"labelComponent","name":null,"preview":null,"value":"{catalogNumber}","defaultValue":null,"dataIndex":"","borderStatus":{"top":true,"right":true,"bottom":true,"left":true},"borderWidth":0,"borderColor":"#000000","borderStyle":"none","backgroundColor":"","useFlexHeight":true,"isEditable":false,"autoShrink":false,"isPlainHTML":false,"padding":{"top":0.08,"right":0.08,"bottom":0.08,"left":0.08},"conditionalFormats":[],"enableArrayFunctions":true,"lockPosition":false,"fontFamily":"opensans","fontAlign":"left","fontSize":12,"fontType":[],"fontColor":"#000000","valign":"top","lineHeight":1.15,"textDirection":"ltr","textColumns":1,"dynamicFontSize":false,"formatter":{"type":"text","values":null}},{"id":"","top":0,"left":0,"width":2.65,"height":0,"zindex":1000,"phpClassName":"Reports_Component_CustomText","className":null,"cls":"labelComponent","name":null,"preview":null,"value":"{category}","defaultValue":null,"dataIndex":"","borderStatus":{"top":true,"right":true,"bottom":true,"left":true},"borderWidth":0,"borderColor":"#000000","borderStyle":"none","backgroundColor":"","useFlexHeight":true,"isEditable":false,"autoShrink":false,"isPlainHTML":false,"padding":{"top":0.08,"right":0.08,"bottom":0.08,"left":0.08},"conditionalFormats":[],"enableArrayFunctions":true,"lockPosition":false,"fontFamily":"opensans","fontAlign":"left","fontSize":12,"fontType":[],"fontColor":"#000000","valign":"top","lineHeight":1.15,"textDirection":"ltr","textColumns":1,"dynamicFontSize":false,"formatter":{"type":"text","values":null}},{"id":"","top":0,"left":0,"width":2.65,"height":0,"zindex":1000,"phpClassName":"Reports_Component_CustomText","className":null,"cls":"labelComponent","name":null,"preview":null,"value":"{description}","defaultValue":null,"dataIndex":"","borderStatus":{"top":true,"right":true,"bottom":true,"left":true},"borderWidth":0,"borderColor":"#000000","borderStyle":"none","backgroundColor":"","useFlexHeight":true,"isEditable":false,"autoShrink":false,"isPlainHTML":false,"padding":{"top":0.08,"right":0.08,"bottom":0.08,"left":0.08},"conditionalFormats":[],"enableArrayFunctions":true,"lockPosition":false,"fontFamily":"opensans","fontAlign":"left","fontSize":12,"fontType":[],"fontColor":"#000000","valign":"top","lineHeight":1.15,"textDirection":"ltr","textColumns":1,"dynamicFontSize":false,"formatter":{"type":"text","values":null}},{"id":"","top":0,"left":0,"width":2.65,"height":0,"zindex":1000,"phpClassName":"Reports_Component_CustomText","className":null,"cls":"labelComponent","name":null,"preview":null,"value":"{id}","defaultValue":null,"dataIndex":"","borderStatus":{"top":true,"right":true,"bottom":true,"left":true},"borderWidth":0,"borderColor":"#000000","borderStyle":"none","backgroundColor":"","useFlexHeight":true,"isEditable":false,"autoShrink":false,"isPlainHTML":false,"padding":{"top":0.08,"right":0.08,"bottom":0.08,"left":0.08},"conditionalFormats":[],"enableArrayFunctions":true,"lockPosition":false,"fontFamily":"opensans","fontAlign":"left","fontSize":12,"fontType":[],"fontColor":"#000000","valign":"top","lineHeight":1.15,"textDirection":"ltr","textColumns":1,"dynamicFontSize":false,"formatter":{"type":"text","values":null}},{"id":"","top":0,"left":0,"width":2.65,"height":0,"zindex":1000,"phpClassName":"Reports_Component_CustomText","className":null,"cls":"labelComponent","name":null,"preview":null,"value":"{image}","defaultValue":null,"dataIndex":"","borderStatus":{"top":true,"right":true,"bottom":true,"left":true},"borderWidth":0,"borderColor":"#000000","borderStyle":"none","backgroundColor":"","useFlexHeight":true,"isEditable":false,"autoShrink":false,"isPlainHTML":false,"padding":{"top":0.08,"right":0.08,"bottom":0.08,"left":0.08},"conditionalFormats":[],"enableArrayFunctions":true,"lockPosition":false,"fontFamily":"opensans","fontAlign":"left","fontSize":12,"fontType":[],"fontColor":"#000000","valign":"top","lineHeight":1.15,"textDirection":"ltr","textColumns":1,"dynamicFontSize":false,"formatter":{"type":"text","values":null}},{"id":"","top":0,"left":0,"width":2.65,"height":0,"zindex":1000,"phpClassName":"Reports_Component_CustomText","className":null,"cls":"labelComponent","name":null,"preview":null,"value":"{name}","defaultValue":null,"dataIndex":"","borderStatus":{"top":true,"right":true,"bottom":true,"left":true},"borderWidth":0,"borderColor":"#000000","borderStyle":"none","backgroundColor":"","useFlexHeight":true,"isEditable":false,"autoShrink":false,"isPlainHTML":false,"padding":{"top":0.08,"right":0.08,"bottom":0.08,"left":0.08},"conditionalFormats":[],"enableArrayFunctions":true,"lockPosition":false,"fontFamily":"opensans","fontAlign":"left","fontSize":12,"fontType":[],"fontColor":"#000000","valign":"top","lineHeight":1.15,"textDirection":"ltr","textColumns":1,"dynamicFontSize":false,"formatter":{"type":"text","values":null}}]}],"isDynamic":false,"hideHeaderIfEmpty":true,"pivotOn":[],"pivotColumns":[],"pivotValues":[],"sortBy":[],"sortDir":"ASC","filterBy":[],"groupBy":[],"fontValign":"top"},{"id":"","top":13.99,"left":2.01,"width":0.53,"height":0.53,"zindex":1005,"className":null,"cls":"checkboxComponent","value":1,"dataIndex":"","borderStatus":{"top":true,"right":true,"bottom":true,"left":true},"borderWidth":1,"borderColor":"#000000","borderStyle":"solid","backgroundColor":"","useFlexHeight":true,"isEditable":false,"autoShrink":false,"isPlainHTML":false,"padding":{"top":0,"right":0.2,"bottom":0,"left":0},"conditionalFormats":[],"enableArrayFunctions":true,"lockPosition":false,"fontFamily":"zapfdingbats","fontAlign":"center","fontSize":24,"fontType":[],"fontColor":"#000000","lineHeight":1.15,"textDirection":"ltr","textColumns":1,"dynamicFontSize":false,"fontValign":"middle"}],"margins":{"right":0.5,"bottom":0.5},"border":false},{"width":14.8,"height":21,"conditionalFormats":[],"backgroundImage":null,"layout":[],"components":[],"margins":{"right":0.5,"bottom":0.5},"border":false}],"dataSettings":{"sortBy":[],"filterBy":[],"transform":[]},"editor":{"heightMultiplier":1},"fontSubsetting":false,"barcodeAsImage":false,"backgroundPdf":""}